Metadata-Version: 1.2
Name: elephantsql-cli
Version: 0.0.2
Summary: CLI implementation of the ElephantSQL API
Home-page: https://github.com/flyudvik/elephantsql_cli
Author: Malik S
Author-email: amywoodehy@gmail.com
License: MIT
Download-URL: https://github.com/flyudvik/elephantsql_cli/archive/0.0.2.tar.gz
Platform: UNKNOWN
Classifier: Development Status :: 3 - Alpha
Classifier: Intended Audience :: Developers
Classifier: Topic :: Software Development :: Libraries
Classifier: License :: OSI Approved :: MIT License
Classifier: Programming Language :: Python :: 3.6
Requires-Python: >=0.0.1
